AUTHORS
LICENSE
MANIFEST.in
README.rst
setup.py
django_tinylinks.egg-info/PKG-INFO
django_tinylinks.egg-info/SOURCES.txt
django_tinylinks.egg-info/dependency_links.txt
django_tinylinks.egg-info/requires.txt
django_tinylinks.egg-info/top_level.txt
tinylinks/__init__.py
tinylinks/admin.py
tinylinks/forms.py
tinylinks/models.py
tinylinks/urls.py
tinylinks/utils.py
tinylinks/views.py
tinylinks/management/__init__.py
tinylinks/management/commands/__init__.py
tinylinks/management/commands/check_tinylink_targets.py
tinylinks/migrations/0001_initial.py
tinylinks/migrations/__init__.py
tinylinks/south_migrations/0001_initial.py
tinylinks/south_migrations/0002_auto__add_field_tinylink_user.py
tinylinks/south_migrations/0003_auto__add_field_tinylink_is_broken__add_field_tinylink_last_checked.py
tinylinks/south_migrations/0004_auto__add_field_tinylink_amount_of_views.py
tinylinks/south_migrations/0005_auto__add_field_tinylink_redirect_location.py
tinylinks/south_migrations/0006_auto__add_field_tinylink_validation_error.py
tinylinks/south_migrations/__init__.py
tinylinks/templates/tinylinks/notfound.html
tinylinks/templates/tinylinks/statistics.html
tinylinks/templates/tinylinks/tinylink_confirm_delete.html
tinylinks/templates/tinylinks/tinylink_form.html
tinylinks/templates/tinylinks/tinylink_list.html
tinylinks/tests/__init__.py
tinylinks/tests/check_tinylink_targets_tests.py
tinylinks/tests/forms_tests.py
tinylinks/tests/models_tests.py
tinylinks/tests/settings.py
tinylinks/tests/test_settings.py
tinylinks/tests/urls.py
tinylinks/tests/utils_tests.py
tinylinks/tests/views.py
tinylinks/tests/views_tests.py
tinylinks/tests/test_app/__init__.py
tinylinks/tests/test_app/models.py
tinylinks/tests/test_app/fixtures/auth.json
tinylinks/tests/test_app/fixtures/sites.json
tinylinks/tests/test_app/fixtures/tinylinks.json
tinylinks/tests/test_app/templates/404.html
tinylinks/tests/test_app/templates/500.html
tinylinks/tests/test_app/templates/base.html