Metadata-Version: 1.0
Name: django-tinylinks
Version: 0.7
Summary: A reusable Django app that adds a link shortener like bit.ly to your site.
